ft8decoder/__init__.py
ft8decoder/cli.py
ft8decoder/core.py
ft8decoder/parser.py
ft8decoder/processor.py
ft8decoder-0.1.8.dist-info/LICENSE.txt
ft8decoder-0.1.8.dist-info/METADATA
ft8decoder-0.1.8.dist-info/WHEEL
ft8decoder-0.1.8.dist-info/entry_points.txt
ft8decoder-0.1.8.dist-info/RECORD
