Metadata-Version: 2.3
Name: ft8decoder
Version: 0.1.8
Summary: An FT8 message logger that tracks, translates, and organizes CQs, QSOs, and Misc. messages from live WSJT-X packets.
License: MIT
Author: Christopher Cottone
Author-email: chriscottone1@gmail.com
Requires-Python: >=3.8,<4.0
Classifier: Development Status :: 3 - Alpha
Classifier: Intended Audience :: Developers
Classifier: Intended Audience :: Science/Research
Classifier: License :: OSI Approved :: MIT License
Classifier: Operating System :: OS Independent
Classifier: Programming Language :: Python :: 3
Classifier: Programming Language :: Python :: 3.8
Classifier: Programming Language :: Python :: 3.9
Classifier: Programming Language :: Python :: 3.10
Classifier: Programming Language :: Python :: 3.11
Classifier: Programming Language :: Python :: 3.12
Classifier: Programming Language :: Python :: 3.13
Classifier: Topic :: Communications :: Ham Radio
Classifier: Topic :: Scientific/Engineering
Requires-Dist: folium
Requires-Dist: maidenhead
Project-URL: Documentation, https://zappathehackka.github.io/ft8decoder/
Project-URL: Homepage, https://github.com/ZappatheHackka/ft8decoder
Project-URL: Repository, https://github.com/ZappatheHackka/ft8decoder
